Topsis_Garvit_102017132/topsis.py
topsis/102017132.py
topsis/__init__.py
topsis/__main__.py
Topsis_Garvit_102017132-1.0.7.dist-info/LICENSE
Topsis_Garvit_102017132-1.0.7.dist-info/METADATA
Topsis_Garvit_102017132-1.0.7.dist-info/WHEEL
Topsis_Garvit_102017132-1.0.7.dist-info/entry_points.txt
Topsis_Garvit_102017132-1.0.7.dist-info/top_level.txt
Topsis_Garvit_102017132-1.0.7.dist-info/RECORD
