Metadata-Version: 2.1
Name: Topsis-Garvit-102017132
Version: 1.0.7
Summary: This is a Python library for handling problems related to Multiple Criteria Decision Making(MCDM)
Home-page: https://github.com/Garvit-Batra/Topsis-Garvit-102017132
Author: Garvit Batra
Author-email: batra.garvit28@gmail.com
License: MIT
Platform: UNKNOWN
Classifier: License :: OSI Approved :: MIT License
Classifier: Programming Language :: Python :: 3.6
Classifier: Programming Language :: Python :: 3.7
Classifier: Programming Language :: Python :: 3.8
License-File: LICENSE
Requires-Dist: pandas
